fuzzyops/__init__.py
fuzzyops/fan/__init__.py
fuzzyops/fan/fan.py
fuzzyops/fuzzy_logic/__init__.py
fuzzyops/fuzzy_logic/base_rules.py
fuzzyops/fuzzy_msa/__init__.py
fuzzyops/fuzzy_msa/msa_fuzzy_hierarchy.py
fuzzyops/fuzzy_msa/msa_fuzzy_pairwise.py
fuzzyops/fuzzy_msa/msa_fuzzy_pareto.py
fuzzyops/fuzzy_msa/msa_fuzzy_sum.py
fuzzyops/fuzzy_neural_net/__init__.py
fuzzyops/fuzzy_neural_net/layer.py
fuzzyops/fuzzy_neural_net/network.py
fuzzyops/fuzzy_neural_net/neuron.py
fuzzyops/fuzzy_neural_net/synapse.py
fuzzyops/fuzzy_nn/__init__.py
fuzzyops/fuzzy_nn/mf_funcs.py
fuzzyops/fuzzy_nn/model.py
fuzzyops/fuzzy_numbers/__init__.py
fuzzyops/fuzzy_numbers/fuzzify/__init__.py
fuzzyops/fuzzy_numbers/fuzzify/defuzz.py
fuzzyops/fuzzy_numbers/fuzzify/fuzzy_number.py
fuzzyops/fuzzy_numbers/fuzzify/mf.py
fuzzyops/fuzzy_numbers/fuzzify/fmath/__init__.py
fuzzyops/fuzzy_numbers/fuzzify/fmath/logic.py
fuzzyops/fuzzy_numbers/fuzzify/fmath/operations.py
fuzzyops/fuzzy_optimization/__init__.py
fuzzyops/fuzzy_optimization/fuzzy_linear_optimization/__init__.py
fuzzyops/fuzzy_optimization/fuzzy_linear_optimization/optimization.py
fuzzyops/fuzzy_optimization/fuzzy_metaevristic_optimization/__init__.py
fuzzyops/fuzzy_optimization/fuzzy_metaevristic_optimization/optimization.py
fuzzyops/graphs/__init__.py
fuzzyops/graphs/algorithms/__init__.py
fuzzyops/graphs/algorithms/dominating/__init__.py
fuzzyops/graphs/algorithms/dominating/dominating_set.py
fuzzyops/graphs/algorithms/dominating/fuzzy_dominating_set.py
fuzzyops/graphs/algorithms/dominating/is_dominating.py
fuzzyops/graphs/algorithms/factoring/__init__.py
fuzzyops/graphs/algorithms/factoring/mle_clusterization_factors.py
fuzzyops/graphs/algorithms/transport/__init__.py
fuzzyops/graphs/algorithms/transport/shortest_path.py
fuzzyops/graphs/fuzzgraph/__init__.py
fuzzyops/graphs/fuzzgraph/graph.py
fuzzyops/graphs/fuzzgraph/edges/__init__.py
fuzzyops/graphs/fuzzgraph/edges/base_edge.py
fuzzyops/graphs/fuzzgraph/edges/dir_edge.py
fuzzyops-1.0.16.dist-info/LICENSE
fuzzyops-1.0.16.dist-info/METADATA
fuzzyops-1.0.16.dist-info/WHEEL
fuzzyops-1.0.16.dist-info/top_level.txt
fuzzyops-1.0.16.dist-info/RECORD
